crypto/__init__.py
crypto/constants.py
crypto/exceptions.py
crypto/configuration/__init__.py
crypto/configuration/fee.py
crypto/configuration/network.py
crypto/identity/__init__.py
crypto/identity/address.py
crypto/identity/private_key.py
crypto/identity/public_key.py
crypto/identity/wif.py
crypto/networks/__init__.py
crypto/networks/devnet.py
crypto/networks/mainnet.py
crypto/networks/testnet.py
crypto/schnorr/__init__.py
crypto/schnorr/schnorr.py
crypto/transactions/__init__.py
crypto/transactions/deserializer.py
crypto/transactions/serializer.py
crypto/transactions/transaction.py
crypto/transactions/builder/__init__.py
crypto/transactions/builder/base.py
crypto/transactions/builder/delegate_registration.py
crypto/transactions/builder/delegate_resignation.py
crypto/transactions/builder/htlc_claim.py
crypto/transactions/builder/htlc_lock.py
crypto/transactions/builder/htlc_refund.py
crypto/transactions/builder/ipfs.py
crypto/transactions/builder/multi_payment.py
crypto/transactions/builder/multi_signature_registration.py
crypto/transactions/builder/second_signature_registration.py
crypto/transactions/builder/transfer.py
crypto/transactions/builder/vote.py
crypto/transactions/deserializers/__init__.py
crypto/transactions/deserializers/base.py
crypto/transactions/deserializers/delegate_registration.py
crypto/transactions/deserializers/delegate_resignation.py
crypto/transactions/deserializers/htlc_claim.py
crypto/transactions/deserializers/htlc_lock.py
crypto/transactions/deserializers/htlc_refund.py
crypto/transactions/deserializers/ipfs.py
crypto/transactions/deserializers/multi_payment.py
crypto/transactions/deserializers/multi_signature_registration.py
crypto/transactions/deserializers/second_signature_registration.py
crypto/transactions/deserializers/transfer.py
crypto/transactions/deserializers/vote.py
crypto/transactions/serializers/__init__.py
crypto/transactions/serializers/base.py
crypto/transactions/serializers/delegate_registration.py
arkecosystem_crypto-2.0.0.dist-info/LICENSE
arkecosystem_crypto-2.0.0.dist-info/METADATA
arkecosystem_crypto-2.0.0.dist-info/WHEEL
arkecosystem_crypto-2.0.0.dist-info/top_level.txt
arkecosystem_crypto-2.0.0.dist-info/RECORD
